{"is_source_file": true, "format": "Kotlin", "description": "Data class representing a Note with properties such as title, content, tags, and timestamps.", "external_files": [], "external_methods": ["System.currentTimeMillis"], "published": ["org.example.app.data.Note"], "classes": [{"name": "Note", "description": "A data class modeling a Note with id, title, content, tags, createdAt, and updatedAt fields."}], "methods": [{"name": "Note", "description": "Primary constructor for the Note data class, initializing fields with provided values or defaults."}], "calls": ["System.currentTimeMillis"], "search-terms": ["Note", "data class", "tags", "createdAt", "updatedAt", "id", "title", "content"], "state": 2, "file_id": 5, "knowledge_revision": 63, "git_revision": "", "revision_history": [{"17": ""}, {"63": ""}], "hash": "c175cf31da201fdd9e4a6dc5aa12b86c", "format-version": 4, "code-base-name": "android_frontend", "filename": "android_frontend/app/src/main/kotlin/org/example/app/data/Note.kt"}